dynamodol/__init__.py
dynamodol-0.0.2.dist-info/LICENSE
dynamodol-0.0.2.dist-info/METADATA
dynamodol-0.0.2.dist-info/WHEEL
dynamodol-0.0.2.dist-info/top_level.txt
dynamodol-0.0.2.dist-info/RECORD
