Metadata-Version: 2.1
Name: dynamodol
Version: 0.0.2
Summary: dynamodb (through boto3) with a simple (dict-like or list-like) interface
Home-page: https://github.com/i2mint/dynamodol
Author: OtoSense
License: apache-2.0
Keywords: dynamodb,dynamo,aws,data access
Platform: any
Requires-Dist: dol
Requires-Dist: botocore
Requires-Dist: boto3
